scdef/__init__.py
scdef/models/__init__.py
scdef/models/_iscdef.py
scdef/models/_scdef.py
scdef/plotting/__init__.py
scdef/plotting/factors.py
scdef/plotting/graph.py
scdef/plotting/qc.py
scdef/utils/__init__.py
scdef/utils/color_utils.py
scdef/utils/data_utils.py
scdef/utils/factor_utils.py
scdef/utils/hierarchy_utils.py
scdef/utils/jax_utils.py
scdef/utils/score_utils.py
scdef-0.3.5.dist-info/METADATA
scdef-0.3.5.dist-info/WHEEL
scdef-0.3.5.dist-info/RECORD
