Metadata-Version: 2.3
Name: scdef
Version: 0.3.5
Summary: Extract hierarchical signatures of cell state from single-cell data.
Home-page: https://github.com/cbg-ethz/scdef
License: MIT
Author: pedrofale
Author-email: pedro.miguel.ferreira.pf@gmail.com
Requires-Python: >=3.10,<3.12
Classifier: License :: OSI Approved :: MIT License
Classifier: Programming Language :: Python :: 3
Classifier: Programming Language :: Python :: 3.10
Classifier: Programming Language :: Python :: 3.11
Requires-Dist: anndata (>=0.10.5,<0.11.0)
Requires-Dist: click (>=8.0.1,<9.0.0)
Requires-Dist: decoupler (>=1.7.0,<2.0.0)
Requires-Dist: graphviz (>=0.14.2,<0.15.0)
Requires-Dist: igraph (>=0.10.4,<0.11.0)
Requires-Dist: jax (>=0.4.31)
Requires-Dist: jaxlib (>=0.4.31)
Requires-Dist: numba (>=0.60.0,<0.61.0)
Requires-Dist: numpy (>=1.26.4,<2.0.0)
Requires-Dist: optax (>=0.2.3,<0.3.0)
Requires-Dist: pandas (>=2.2.2,<3.0.0)
Requires-Dist: scanpy (>=1.9.5,<2.0.0)
Requires-Dist: tensorflow-probability (>=0.24.0,<0.25.0)
Requires-Dist: tqdm (>=4.64.0,<5.0.0)
Project-URL: Repository, https://github.com/cbg-ethz/scdef
